caf_ai-0.1.0.dist-info/METADATA
caf_ai-0.1.0.dist-info/WHEEL
caf_ai/__init__.py
caf_ai/__pycache__/__init__.cpython-311.pyc
caf_ai/_internal.abi3.so
caf_ai/py.typed
caf_ai-0.1.0.dist-info/RECORD
