Metadata-Version: 2.4
Name: caf-ai
Version: 0.1.0
Classifier: Development Status :: 4 - Beta
Classifier: Intended Audience :: Developers
Classifier: Intended Audience :: System Administrators
Classifier: License :: OSI Approved :: MIT License
Classifier: Programming Language :: Python :: 3
Classifier: Programming Language :: Python :: 3.8
Classifier: Programming Language :: Python :: 3.9
Classifier: Programming Language :: Python :: 3.10
Classifier: Programming Language :: Python :: 3.11
Classifier: Programming Language :: Python :: 3.12
Classifier: Programming Language :: Rust
Classifier: Topic :: Security
Classifier: Topic :: Software Development :: Libraries :: Python Modules
Classifier: Topic :: Scientific/Engineering :: Artificial Intelligence
Classifier: Typing :: Typed
Requires-Dist: pytest>=7.0 ; extra == 'dev'
Requires-Dist: pytest-asyncio>=0.21.0 ; extra == 'dev'
Requires-Dist: black>=23.0 ; extra == 'dev'
Requires-Dist: mypy>=1.0 ; extra == 'dev'
Requires-Dist: ruff>=0.1.0 ; extra == 'dev'
Provides-Extra: dev
Summary: Context-Aware Firewall for AI Systems - High-performance security detection
Keywords: ai-security,prompt-injection,llm-security,ai-safety,security,firewall,detection,rust
Author: CAF-AI Contributors
Author-email: CAF-AI Contributors <security@caf-ai.dev>
License: MIT
Requires-Python: >=3.8
Project-URL: Homepage, https://github.com/ihabbishara/caf-ai
Project-URL: Documentation, https://github.com/ihabbishara/caf-ai#readme
Project-URL: Repository, https://github.com/ihabbishara/caf-ai
Project-URL: Issues, https://github.com/ihabbishara/caf-ai/issues
Project-URL: Changelog, https://github.com/ihabbishara/caf-ai/releases
